atmospheric_lidar/__init__.py
atmospheric_lidar/diva.py
atmospheric_lidar/generic.py
atmospheric_lidar/licel.py
atmospheric_lidar/licel_depol.py
atmospheric_lidar/licelv2.py
atmospheric_lidar/raymetrics.py
atmospheric_lidar/scripts/__init__.py
atmospheric_lidar/scripts/licel2scc.py
atmospheric_lidar/scripts/licel2scc_depol.py
atmospheric_lidar/scripts/licel2tc.py
atmospheric_lidar/systems/__init__.py
atmospheric_lidar/systems/ciao.py
dist/atmospheric_lidar-0.4.4-py3-none-any.whl
dist/atmospheric_lidar-0.4.4.tar.gz
atmospheric_lidar-0.5.4.dist-info/LICENCE.txt
atmospheric_lidar-0.5.4.dist-info/METADATA
atmospheric_lidar-0.5.4.dist-info/WHEEL
atmospheric_lidar-0.5.4.dist-info/entry_points.txt
atmospheric_lidar-0.5.4.dist-info/top_level.txt
atmospheric_lidar-0.5.4.dist-info/RECORD
