Metadata-Version: 2.1
Name: atmospheric-lidar
Version: 0.5.4
Summary: Package for reading raw atmospheric lidar data.
Home-page: https://bitbucket.org/iannis_b/atmospheric-lidar/
Author: Ioannis Binietoglou
Author-email: ioannis@inoe.ro
License: MIT
Keywords: lidar aerosol licel SCC
Platform: UNKNOWN
Classifier: Development Status :: 3 - Alpha
Classifier: License :: OSI Approved :: MIT License
Classifier: Programming Language :: Python :: 2
Classifier: Programming Language :: Python :: 3
Classifier: Intended Audience :: Science/Research
Classifier: Topic :: Scientific/Engineering :: Atmospheric Science
Requires-Dist: matplotlib
Requires-Dist: netCDF4
Requires-Dist: numpy
Requires-Dist: numpydoc
Requires-Dist: pytz
Requires-Dist: pyyaml
Requires-Dist: sphinx
